napari_label_interpolator/__init__.py
napari_label_interpolator/_version.py
napari_label_interpolator/interpolator.py
napari_label_interpolator/napari.yaml
napari_label_interpolator/_tests/__init__.py
napari_label_interpolator/_tests/test_widget.py
napari_label_interpolator-0.1.1.dist-info/LICENSE
napari_label_interpolator-0.1.1.dist-info/METADATA
napari_label_interpolator-0.1.1.dist-info/WHEEL
napari_label_interpolator-0.1.1.dist-info/entry_points.txt
napari_label_interpolator-0.1.1.dist-info/top_level.txt
napari_label_interpolator-0.1.1.dist-info/RECORD
