Metadata-Version: 2.1
Name: napari-label-interpolator
Version: 0.1.1
Summary: A napari plugin to interpolate any number of nd-labels across a single dimension.
Home-page: https://github.com/brisvag/napari-label-interpolator
Author: Lorenzo Gaifas
Author-email: brisvag@gmail.com
License: GPL-3.0-only
Project-URL: Bug Tracker, https://github.com/brisvag/napari-label-interpolator/issues
Project-URL: Documentation, https://github.com/brisvag/napari-label-interpolator#README.md
Project-URL: Source Code, https://github.com/brisvag/napari-label-interpolator
Project-URL: User Support, https://github.com/brisvag/napari-label-interpolator/issues
Classifier: Development Status :: 2 - Pre-Alpha
Classifier: Framework :: napari
Classifier: Intended Audience :: Developers
Classifier: License :: OSI Approved :: GNU General Public License v3 (GPLv3)
Classifier: Operating System :: OS Independent
Classifier: Programming Language :: Python
Classifier: Programming Language :: Python :: 3
Classifier: Programming Language :: Python :: 3 :: Only
Classifier: Programming Language :: Python :: 3.8
Classifier: Programming Language :: Python :: 3.9
Classifier: Programming Language :: Python :: 3.10
Classifier: Topic :: Scientific/Engineering :: Image Processing
Requires-Python: >=3.8
License-File: LICENSE
Requires-Dist: magicgui
Requires-Dist: edt
Provides-Extra: testing
Requires-Dist: tox ; extra == 'testing'
Requires-Dist: pytest ; extra == 'testing'
Requires-Dist: pytest-cov ; extra == 'testing'
Requires-Dist: pytest-qt ; extra == 'testing'
Requires-Dist: napari ; extra == 'testing'
Requires-Dist: pyqt5 ; extra == 'testing'
